deel/torchlip/VERSION
deel/torchlip/__init__.py
deel/torchlip/functional.py
deel/torchlip/init.py
deel/torchlip/normalizers.py
deel/torchlip/modules/__init__.py
deel/torchlip/modules/activation.py
deel/torchlip/modules/conv.py
deel/torchlip/modules/downsampling.py
deel/torchlip/modules/linear.py
deel/torchlip/modules/loss.py
deel/torchlip/modules/module.py
deel/torchlip/modules/normalization.py
deel/torchlip/modules/pooling.py
deel/torchlip/modules/residual.py
deel/torchlip/modules/unconstrained.py
deel/torchlip/modules/upsampling.py
deel/torchlip/utils/__init__.py
deel/torchlip/utils/bjorck_norm.py
deel/torchlip/utils/evaluate_lip_const.py
deel/torchlip/utils/frobenius_norm.py
deel/torchlip/utils/lconv_norm.py
deel/torchlip/utils/sqrt_eps.py
deel_torchlip-1.0.4.dist-info/licenses/LICENSE
deel_torchlip-1.0.4.dist-info/METADATA
deel_torchlip-1.0.4.dist-info/WHEEL
deel_torchlip-1.0.4.dist-info/top_level.txt
deel_torchlip-1.0.4.dist-info/RECORD
