Metadata-Version: 2.4
Name: deel-torchlip
Version: 1.0.4
Summary: PyTorch implementation for k-Lipschitz layers
Home-page: https://github.com/deel-ai/deel-torchlip
Author: Mathieu SERRURIER, Franck MAMALET, Thibaut BOISSIN, Mikaël CAPELLE, Justin PLAKOO
Author-email: mathieu.serrurier@irt-saintexupery.com, franck.mamalet@irt-saintexupery.com, thibaut.boissin@irt-saintexupery.com, justin.plakoo@irt-saintexupery.com
License: MIT
Classifier: Programming Language :: Python :: 3
Classifier: Programming Language :: Python :: 3.6
Classifier: Programming Language :: Python :: 3.7
Classifier: Programming Language :: Python :: 3.8
Classifier: License :: OSI Approved :: MIT License
Classifier: Operating System :: OS Independent
Requires-Python: >=3.6
License-File: LICENSE
Requires-Dist: numpy
Requires-Dist: torch
Provides-Extra: dev
Requires-Dist: tox; extra == "dev"
Requires-Dist: black; extra == "dev"
Requires-Dist: flake8; extra == "dev"
Requires-Dist: flake8-black; extra == "dev"
Requires-Dist: numpy; extra == "dev"
Requires-Dist: torch_testing; extra == "dev"
Provides-Extra: doc
Requires-Dist: sphinx==3.3.1; extra == "doc"
Requires-Dist: recommonmark; extra == "doc"
Requires-Dist: sphinx_rtd_theme; extra == "doc"
Requires-Dist: sphinx_markdown_builder; extra == "doc"
Requires-Dist: ipython; extra == "doc"
Requires-Dist: nbsphinx; extra == "doc"
Requires-Dist: sphinxcontrib_katex; extra == "doc"
Requires-Dist: pytorch_sphinx_theme; extra == "doc"
Dynamic: author
Dynamic: author-email
Dynamic: classifier
Dynamic: description
Dynamic: description-content-type
Dynamic: home-page
Dynamic: license
Dynamic: license-file
Dynamic: provides-extra
Dynamic: requires-dist
Dynamic: requires-python
Dynamic: summary
